attachtags/__init__.py
attachtags/argtomap.py
attachtags/attachtags.py
attachtags/cli.py
attachtags/parserbuilder.py
attachtags/tagmaps.py
attachtags-0.1.3.dist-info/AUTHORS.rst
attachtags-0.1.3.dist-info/LICENSE
attachtags-0.1.3.dist-info/METADATA
attachtags-0.1.3.dist-info/WHEEL
attachtags-0.1.3.dist-info/entry_points.txt
attachtags-0.1.3.dist-info/top_level.txt
attachtags-0.1.3.dist-info/RECORD
