Metadata-Version: 2.1
Name: attachtags
Version: 0.1.3
Summary: attachtags is a tool for recording and categorizing files in your Windows.
Home-page: https://github.com/Gongzi-Yu/attachtags
Author: Gongzi Yu
Author-email: 1920781522@qq.com
License: MIT license
Project-URL: Bug Tracker, https://github.com/Gongzi-Yu/attachtags/issues
Keywords: attachtags
Platform: UNKNOWN
Classifier: Programming Language :: Python :: 3.7
Classifier: License :: OSI Approved :: MIT License
Classifier: Operating System :: OS Independent
Requires-Python: >=3.7.3
License-File: LICENSE
License-File: AUTHORS.rst
Requires-Dist: setuptools (>=42)
Requires-Dist: wheel
